{
  "area": {
    "direction": -1,
    "placement": {
      "angle": 0,
      "position": [
        0,
        46.0478999999996
      ]
    },
    "points": [
      {
        "anchor": [
          1059.9854,
          0
        ],
        "leftPosition": [
          1059.9854,
          0
        ],
        "rightPosition": [
          1058.1719,
          0.33350000000064
        ]
      },
      {
        "anchor": [
          1054.5742,
          0.99020000000019
        ],
        "leftPosition": [
          1056.3643,
          0.66500000000087
        ],
        "rightPosition": [
          1040.4346,
          3.5614999999998
        ]
      },
      {
        "anchor": [
          1011.6836,
          8.43950000000041
        ],
        "leftPosition": [
          1026.0039,
          6.06840000000011
        ],
        "rightPosition": [
          861.056578247881,
          33.3931000000011
        ]
      },
      {
        "anchor": [
          552.778786035633,
          46.0478999999996
        ],
        "leftPosition": [
          706.660182148262,
          46.0478999999996
        ],
        "rightPosition": [
          398.867189923767,
          46.0478999999996
        ]
      },
      {
        "anchor": [
          93.7686000000003,
          8.42190000000119
        ],
        "leftPosition": [
          244.432593825113,
          33.3886999999995
        ],
        "rightPosition": [
          78.6943000000001,
          5.92330000000038
        ]
      },
      {
        "anchor": [
          48.4296999999997,
          0.52440000000024
        ],
        "leftPosition": [
          63.4423999999999,
          3.26710000000094
        ],
        "rightPosition": [
          47.4790000000003,
          0.35059999999976
        ]
      },
      {
        "anchor": [
          45.5806000000002,
          0
        ],
        "leftPosition": [
          46.5303000000004,
          0.17480000000069
        ],
        "rightPosition": [
          45.5806000000002,
          0
        ]
      },
      {
        "anchor": [
          0,
          0
        ],
        "leftPosition": [
          0,
          0
        ],
        "rightPosition": [
          0,
          0
        ]
      },
      {
        "anchor": [
          0,
          -1260
        ],
        "leftPosition": [
          0,
          -1260
        ],
        "rightPosition": [
          0,
          -1260
        ]
      },
      {
        "anchor": [
          45.5806000000002,
          -1260
        ],
        "leftPosition": [
          45.5806000000002,
          -1260
        ],
        "rightPosition": [
          46.5303000000004,
          -1259.825195
        ]
      },
      {
        "anchor": [
          48.4296999999997,
          -1259.475586
        ],
        "leftPosition": [
          47.4790000000003,
          -1259.649414
        ],
        "rightPosition": [
          63.4423999999999,
          -1256.73242
        ]
      },
      {
        "anchor": [
          93.7686000000003,
          -1251.57812
        ],
        "leftPosition": [
          78.6943000000001,
          -1254.07617
        ],
        "rightPosition": [
          244.432593825113,
          -1226.6113
        ]
      },
      {
        "anchor": [
          552.778786035633,
          -1213.9521
        ],
        "leftPosition": [
          398.867189923767,
          -1213.9521
        ],
        "rightPosition": [
          706.660182148262,
          -1213.9521
        ]
      },
      {
        "anchor": [
          1011.6836,
          -1251.56055
        ],
        "leftPosition": [
          861.056578247881,
          -1226.6074
        ],
        "rightPosition": [
          1026.0039,
          -1253.93164
        ]
      },
      {
        "anchor": [
          1054.5742,
          -1259.009766
        ],
        "leftPosition": [
          1040.4346,
          -1256.43848
        ],
        "rightPosition": [
          1056.3643,
          -1259.334961
        ]
      },
      {
        "anchor": [
          1059.9854,
          -1260
        ],
        "leftPosition": [
          1058.1719,
          -1259.666016
        ],
        "rightPosition": [
          1059.9854,
          -1260
        ]
      },
      {
        "anchor": [
          1105.5117,
          -1260
        ],
        "leftPosition": [
          1105.5117,
          -1260
        ],
        "rightPosition": [
          1105.5117,
          -1260
        ]
      },
      {
        "anchor": [
          1105.5117,
          0
        ],
        "leftPosition": [
          1105.5117,
          0
        ],
        "rightPosition": [
          1105.5117,
          0
        ]
      }
    ]
  },
  "cuts": [
    {
      "angle": 0,
      "position": [
        552.75583991042,
        -131.600310592984
      ]
    },
    {
      "angle": 0,
      "position": [
        552.75583991042,
        -446.600225567023
      ]
    },
    {
      "angle": 0,
      "position": [
        552.75583991042,
        -761.600217615962
      ]
    },
    {
      "angle": 0,
      "position": [
        552.75583991042,
        -1076.59995950102
      ]
    }
  ],
  "dimensions": [
    1105.5117,
    1260
  ]
}